{
  "doc_id": "ALS PR 7- Intranasal medications procedure_APR22",
  "file_path": "C:\\Users\\SAHARA\\OneDrive\\Desktop\\uni\\gemma\\risk_score\\rag_store\\sop_pdfs\\ALS PR 7- Intranasal medications procedure_APR22.pdf",
  "pages": [
    {
      "page_num": 1,
      "text": "April 2022 County of Marin EMS ALS PR 7\nINTRANASAL MEDICATION\nADMINISTRATION PROCEDURE\nIndications\n• No IV access with the following symptoms:\n• Status epilepticus\n• Suspected narcotic overdose with respiratory depression\n• Apparent or reported pain level >6\nEquipment\n• MAD adapter (atomizer)\n• Syringe\n• Suction\n• With medication in syringe, attach atomizer\n• Do not lubricate tip\n• Stabilizing the head, place applicator in nares\nand briskly compress the syringe plunger\nSPECIAL CONSIDERATIONS\n• Be attentive to excessive oral recreations,\nvomiting, and adequate tidal volume\nCritical Information\n• Contraindications:\n• Epistaxis\n• Complete mucosal blockage of both nostrils\n• Nasal trauma\n• Any recognizable abnormalities\n• Retropharyngeal lacerations/dissections",
      "image_path": null
    }
  ]
}